soltgbackend/solc_new/solidity/deps/fmtlib/support/docopt.py
soltgbackend/solc_new/solidity/deps/fmtlib/support/manage.py
soltgbackend/solc_new/solidity/deps/fmtlib/support/printable.py
soltgbackend/solc_new/solidity/deps/fmtlib/support/python/mkdocstrings_handlers/cxx/__init__.py
soltgbackend/solc_new/solidity/deps/nlohmann-json/docs/mkdocs/scripts/check_structure.py
soltgbackend/solc_new/solidity/deps/nlohmann-json/tests/thirdparty/imapdl/filterbr.py
soltgbackend/solc_new/solidity/deps/nlohmann-json/tools/amalgamate/amalgamate.py
soltgbackend/solc_new/solidity/deps/nlohmann-json/tools/gdb_pretty_printer/nlohmann-json.py
soltgbackend/solc_new/solidity/deps/nlohmann-json/tools/generate_natvis/generate_natvis.py
soltgbackend/solc_new/solidity/deps/nlohmann-json/tools/serve_header/serve_header.py
soltgbackend/solc_new/solidity/deps/range-v3/conanfile.py
soltgbackend/solc_new/solidity/deps/range-v3/test_package/conanfile.py
soltgbackend/solc_new/solidity/docs/conf.py
soltgbackend/solc_new/solidity/docs/ext/html_extra_template_renderer.py
soltgbackend/solc_new/solidity/docs/ext/remix_code_links.py
soltgbackend/solc_new/solidity/libsmtutil/genz3wrapper.py
soltgbackend/solc_new/solidity/scripts/error_codes.py
soltgbackend/solc_new/solidity/scripts/extract_test_cases.py
soltgbackend/solc_new/solidity/scripts/gas_diff_stats.py
soltgbackend/solc_new/solidity/scripts/isolate_tests.py
soltgbackend/solc_new/solidity/scripts/pylint_all.py
soltgbackend/solc_new/solidity/scripts/regressions.py
soltgbackend/solc_new/solidity/scripts/splitSources.py
soltgbackend/solc_new/solidity/scripts/update_bugs_by_version.py
soltgbackend/solc_new/solidity/scripts/bytecodecompare/prepare_report.py
soltgbackend/solc_new/solidity/scripts/common/cmdline_helpers.py
soltgbackend/solc_new/solidity/scripts/common/git_helpers.py
soltgbackend/solc_new/solidity/scripts/common/rest_api_helpers.py
soltgbackend/solc_new/solidity/scripts/externalTests/benchmark_diff.py
soltg_plus_plus-0.1.16.dist-info/METADATA
soltg_plus_plus-0.1.16.dist-info/WHEEL
soltg_plus_plus-0.1.16.dist-info/entry_points.txt
soltg_plus_plus-0.1.16.dist-info/top_level.txt
soltg_plus_plus-0.1.16.dist-info/RECORD
